pyverse/__init__.py
pyverse/__main__.py
pyverse/sentence.py
pyverse/silabeador.py
pyverse/vars.py
pyverse/word.py
pyverse-1.1.0.dist-info/LICENSE
pyverse-1.1.0.dist-info/METADATA
pyverse-1.1.0.dist-info/WHEEL
pyverse-1.1.0.dist-info/entry_points.txt
pyverse-1.1.0.dist-info/top_level.txt
pyverse-1.1.0.dist-info/RECORD
