Metadata-Version: 2.1
Name: pyverse
Version: 1.1.0
Summary: find syllables and rhymes of words/verses in spanish
Home-page: https://github.com/neburnodrog/Pyverso
Author: Ruben Karlsson
Author-email: neburnodrog@gmail.com
License: MIT
Classifier: License :: OSI Approved :: MIT License
Classifier: Programming Language :: Python :: 3
Classifier: Programming Language :: Python :: 3.8
Requires-Python: >=3.8
License-File: LICENSE
Requires-Dist: Click (==7.1.2)
Requires-Dist: numlet
